ttools/__init__.py
ttools/__main__.py
ttools/callbacks.py
ttools/config.py
ttools/data.py
ttools/database.py
ttools/dataio.py
ttools/debug.py
ttools/interfaces.py
ttools/preprocessing.py
ttools/scaffold.py
ttools/training.py
ttools/utils.py
ttools/version.py
ttools/modules/__init__.py
ttools/modules/image_operators.py
ttools/modules/losses.py
ttools/modules/networks.py
ttools/templates/.gitignore
ttools/templates/Makefile
ttools/templates/README.md
ttools/templates/__init__.py
ttools/templates/callbacks.py
ttools/templates/datasets.py
ttools/templates/default.yml
ttools/templates/eval.py
ttools/templates/interfaces.py
ttools/templates/models.py
ttools/templates/pytest.ini
ttools/templates/setup.py
ttools/templates/test_basic.py
ttools/templates/train.py
ttools/templates/version.py
torch_tools-0.1.5.dist-info/LICENSE.md
torch_tools-0.1.5.dist-info/METADATA
torch_tools-0.1.5.dist-info/WHEEL
torch_tools-0.1.5.dist-info/entry_points.txt
torch_tools-0.1.5.dist-info/top_level.txt
torch_tools-0.1.5.dist-info/RECORD
